<?xml version="1.0" encoding="ISO-8859-1"?><?xml-model href="../../derivatives/shelley-godwin-page.rnc"
  type="application/relax-ng-compact-syntax"?><?xml-stylesheet type="text/xsl"
  href="../../xsl/page-proof.xsl"?>
<surface xmlns="http://www.tei-c.org/ns/1.0" xmlns:sga="http://sga.mith.org/ns/1.0" ulx="0" uly="0"
  lrx="5406" lry="7276" xml:id="ox-ms_shelley_e1-0013" partOf="#ox-ms_shelley_e1">
  <graphic url="../../images/ox/ox-ms_shelley_e1-0013.tif"/>
  <zone type="library">6</zone>
  <zone type="main">
    <line>We'll pass the Eyes</line>
    <line>Of the starry skies</line>
    <line>Into the <mod>
        <del rend="strikethrough">old</del>
        <add place="superlinear">hoar</add>
      </mod> Deep to colonize</line>
    <line>Death Chaos &amp; Night,</line>
    <line>From the sound of our flight</line>
    <line>Shall flee, like <mod>
        <del rend="strikethrough">mists</del>
        <add place="superlinear"><del rend="strikethrough"><hi rend="underline">dust</hi></del>
          mist</add>
      </mod> from a Tempests might</line>
    <line>And earth air &amp; light</line>
    <line>And the Spirit of Might</line>
    <line>Which drives round the Stars in their fiery flight;</line>
    <line>And love, thought, &amp; breath</line>
    <line><del rend="strikethrough">And</del> the powers that quell death,</line>
    <line>Wherever we soar shall assemble beneath!</line>
    <line>And our singing shall build</line>
    <line>In the Void's loose field,</line>
    <line>A world for the spirit of Wisdom to weild<unclear>;</unclear></line>
    <line>We will take our plan</line>
    <line>From the new world of man</line>
    <line>And our work shall be called the Promethean</line>
  </zone>
</surface>
