<?xml version="1.0" encoding="ISO-8859-1"?><?xml-model href="../../derivatives/shelley-godwin-page.rnc"
  type="application/relax-ng-compact-syntax"?><?xml-stylesheet type="text/xsl"
  href="../../xsl/page-proof.xsl"?>
<surface xmlns="http://www.tei-c.org/ns/1.0" xmlns:sga="http://sga.mith.org/ns/1.0"
  xml:id="ox-ms_shelley_e1-0074" partOf="#ox-ms_shelley_e1">
  <graphic url="../../images/ox/ox-ms_shelley_e1-0074.tif"/>
  <zone type="main">
    <line>Panthea</line>
    <line>wandering</line>
    <line>world-</line>
    <line>Tis Jove's <del rend="strikethrough">Heaven</del>-<del rend="strikethrough">walking</del> Herald, Mercury</line>
    <line>Ione</line>
    <line>And who are those with hydra tresses</line>
    <line>And iron wings that climb the wind</line>
    <line>Whom the frowning God represses</line>
    <line>Like vapours steaming up behind,</line>
    <line>Clanging loud, an endless crowd</line>
    <line>Panthea</line>
    <line>These are Joves <del rend="strikethrough">tempest</del>-<del rend="strikethrough">walkin</del>g hounds</line>
    <line>Whom he gluts on groans &amp; blood</line>
    <line>When charioted on sulphurous cloud</line>
    <line>He bursts Heaven's bounds</line>
    <line>Ione</line>
    <line>Are they now led from the thin dead</line>
    <line>On new pangs to be fed?</line>
    <line>as ever</line>
    <line>Panthea</line>
    <line><hi rend="underline">Yes{</hi><del rend="strikethrough underline">:} but</del> The Titan looks firm, <del rend="strikethrough">though</del> not</line>
    <line>^ proud.</line>
  </zone>
</surface>
